Trello2Kanboard-1.2.dist-info/DESCRIPTION.rst
Trello2Kanboard-1.2.dist-info/METADATA
Trello2Kanboard-1.2.dist-info/RECORD
Trello2Kanboard-1.2.dist-info/WHEEL
Trello2Kanboard-1.2.dist-info/entry_points.txt
Trello2Kanboard-1.2.dist-info/metadata.json
Trello2Kanboard-1.2.dist-info/top_level.txt
trello2kanboard/__init__.py
trello2kanboard/__main__.py
trello2kanboard/cli.py
trello2kanboard/commands/__init__.py
trello2kanboard/commands/cmd_import.py
trello2kanboard/commands/cmd_json.py
trello2kanboard/commands/cmd_show.py
trello2kanboard/commands/models.py
trello2kanboard/commands/utils.py
